zhulong3/__init__.py
zhulong3/anhui/__init__.py
zhulong3/anhui/huainan.py
zhulong3/anhui/task.py
zhulong3/anhui/xuancheng.py
zhulong3/fujian/__init__.py
zhulong3/fujian/fuqing.py
zhulong3/fujian/fuzhou.py
zhulong3/fujian/longhai.py
zhulong3/fujian/quanzhou.py
zhulong3/fujian/sanming.py
zhulong3/fujian/task.py
zhulong3/fujian/xiamen.py
zhulong3/fujian/zhangzhou.py
zhulong3/gansu/__init__.py
zhulong3/gansu/shenghui.py
zhulong3/gansu/task.py
zhulong3/guangdong/__init__.py
zhulong3/guangdong/dongguan.py
zhulong3/guangdong/shantou.py
zhulong3/guangdong/shaoguan.py
zhulong3/guangdong/shenghui.py
zhulong3/guangdong/shenzhen.py
zhulong3/guangdong/task.py
zhulong3/guangdong/yangjiang.py
zhulong3/guangdong/yunfu.py
zhulong3/guangdong/zhongshan.py
zhulong3/guangxi/__init__.py
zhulong3/guangxi/baise.py
zhulong3/guangxi/beihai.py
zhulong3/guangxi/fangchenggang.py
zhulong3/guangxi/qinzhou.py
zhulong3/guangxi/shenghui.py
zhulong3/guangxi/task.py
zhulong3/guizhou/__init__.py
zhulong3/guizhou/shenghui.py
zhulong3/guizhou/task.py
zhulong3/hebei/__init__.py
zhulong3/hebei/langfang.py
zhulong3/hebei/shenghui.py
zhulong3/hebei/shijiazhuang.py
zhulong3/hebei/tangshan.py
zhulong3/hebei/task.py
zhulong3/hebei/xingtai.py
zhulong3/heilongjiang/__init__.py
zhulong3/heilongjiang/haerbin.py
zhulong3/heilongjiang/qqhaer.py
zhulong3/heilongjiang/shenghui.py
zhulong3/heilongjiang/task.py
zhulong3/henan/__init__.py
zhulong3/henan/kaifeng.py
zhulong3/henan/pingdingshan.py
zhulong3/henan/puyang.py
zhulong3/henan/sanmenxia.py
zhulong3/henan/task.py
zhulong3/henan/zhengzhou.py
zhulong3/hubei/__init__.py
zhulong3/hunan/__init__.py
zhulong3/hunan/changsha1.py
zhulong3/hunan/changsha2.py
zhulong3/hunan/huaihua.py
zhulong3/hunan/loudi.py
zhulong3/hunan/shaoyang.py
zhulong3/hunan/shenghui.py
zhulong3/hunan/task.py
zhulong3/hunan/wugang.py
zhulong3/hunan/yueyang.py
zhulong3/jiangsu/__init__.py
zhulong3/jiangsu/changzhou.py
zhulong3/jiangsu/nanjing.py
zhulong3/jiangsu/nantong.py
zhulong3/jiangsu/shenghui.py
zhulong3-5.3.14.dist-info/METADATA
zhulong3-5.3.14.dist-info/WHEEL
zhulong3-5.3.14.dist-info/top_level.txt
zhulong3-5.3.14.dist-info/RECORD
